kerykeion/__init__.py
kerykeion/astrological_subject_factory.py
kerykeion/backword.py
kerykeion/chart_data_factory.py
kerykeion/composite_subject_factory.py
kerykeion/context_serializer.py
kerykeion/ephemeris_data_factory.py
kerykeion/fetch_geonames.py
kerykeion/llms.txt
kerykeion/planetary_return_factory.py
kerykeion/py.typed
kerykeion/relationship_score_factory.py
kerykeion/report.py
kerykeion/transits_time_range_factory.py
kerykeion/utilities.py
kerykeion/aspects/__init__.py
kerykeion/aspects/aspects_factory.py
kerykeion/aspects/aspects_utils.py
kerykeion/charts/__init__.py
kerykeion/charts/chart_drawer.py
kerykeion/charts/charts_utils.py
kerykeion/charts/draw_planets.py
kerykeion/charts/draw_planets_legacy.py
kerykeion/charts/templates/aspect_grid_only.xml
kerykeion/charts/templates/chart.xml
kerykeion/charts/templates/wheel_only.xml
kerykeion/charts/themes/black-and-white.css
kerykeion/charts/themes/classic.css
kerykeion/charts/themes/dark-high-contrast.css
kerykeion/charts/themes/dark.css
kerykeion/charts/themes/light.css
kerykeion/charts/themes/strawberry.css
kerykeion/house_comparison/__init__.py
kerykeion/house_comparison/house_comparison_factory.py
kerykeion/house_comparison/house_comparison_utils.py
kerykeion/kr_types/__init__.py
kerykeion/kr_types/chart_template_model.py
kerykeion/kr_types/kerykeion_exception.py
kerykeion/kr_types/kr_literals.py
kerykeion/kr_types/kr_models.py
kerykeion/kr_types/settings_models.py
kerykeion/schemas/__init__.py
kerykeion/schemas/chart_template_model.py
kerykeion/schemas/kerykeion_exception.py
kerykeion/schemas/kr_literals.py
kerykeion/schemas/kr_models.py
kerykeion/schemas/settings_models.py
kerykeion/settings/__init__.py
kerykeion/settings/chart_defaults.py
kerykeion/settings/config_constants.py
kerykeion/settings/kerykeion_settings.py
kerykeion/settings/translation_strings.py
kerykeion/settings/translations.py
kerykeion/sweph/README.md
kerykeion/sweph/seas_18.se1
kerykeion/sweph/sefstars.txt
kerykeion-5.7.1.dist-info/METADATA
kerykeion-5.7.1.dist-info/WHEEL
kerykeion-5.7.1.dist-info/licenses/LICENSE
kerykeion-5.7.1.dist-info/RECORD
