Metadata-Version: 2.4
Name: kerykeion
Version: 5.7.1
Summary: A Python library for astrological calculations, including natal charts, houses, planetary aspects, and SVG chart generation.
Project-URL: Homepage, https://www.kerykeion.net/
Project-URL: Repository, https://github.com/g-battaglia/kerykeion
Author-email: Giacomo Battaglia <kerykeion.astrology@gmail.com>
License: AGPL-3.0
License-File: LICENSE
Keywords: astrology,astrology calculations,astrology calculator,astrology library,astrology transits,astronomical algorithms,birth chart,ephemeris,houses of astrology,natal chart,planetary aspects,svg charts,synastry,zodiac,zodiac signs
Classifier: Development Status :: 5 - Production/Stable
Classifier: Intended Audience :: Developers
Classifier: Intended Audience :: Information Technology
Classifier: Intended Audience :: Science/Research
Classifier: License :: OSI Approved :: GNU General Public License v3 (GPLv3)
Classifier: Operating System :: OS Independent
Classifier: Programming Language :: Python :: 3 :: Only
Classifier: Programming Language :: Python :: 3.9
Classifier: Programming Language :: Python :: 3.10
Classifier: Programming Language :: Python :: 3.11
Classifier: Programming Language :: Python :: 3.12
Classifier: Programming Language :: Python :: 3.13
Classifier: Topic :: Religion
Classifier: Topic :: Scientific/Engineering :: Astronomy
Classifier: Topic :: Scientific/Engineering :: Visualization
Classifier: Topic :: Software Development
Classifier: Topic :: Software Development :: Libraries
Classifier: Topic :: Software Development :: Libraries :: Python Modules
Classifier: Typing :: Typed
Requires-Python: >=3.9
Requires-Dist: pydantic>=2.5
Requires-Dist: pyswisseph>=2.10.3.1
Requires-Dist: pytz>=2024.2
Requires-Dist: requests-cache>=1.2.1
Requires-Dist: requests>=2.32.3
Requires-Dist: scour>=0.38.2
Requires-Dist: simple-ascii-tables>=1.0.0
Requires-Dist: typing-extensions>=4.12.2
